odoo/addons/account_cutoff_accrual_subscription/README.rst
odoo/addons/account_cutoff_accrual_subscription/__init__.py
odoo/addons/account_cutoff_accrual_subscription/__manifest__.py
odoo/addons/account_cutoff_accrual_subscription/i18n/account_cutoff_accrual_subscription.pot
odoo/addons/account_cutoff_accrual_subscription/models/__init__.py
odoo/addons/account_cutoff_accrual_subscription/models/account_cutoff.py
odoo/addons/account_cutoff_accrual_subscription/models/account_cutoff_accrual_subscription.py
odoo/addons/account_cutoff_accrual_subscription/readme/CONFIGURE.rst
odoo/addons/account_cutoff_accrual_subscription/readme/CONTRIBUTORS.rst
odoo/addons/account_cutoff_accrual_subscription/readme/DESCRIPTION.rst
odoo/addons/account_cutoff_accrual_subscription/security/ir.model.access.csv
odoo/addons/account_cutoff_accrual_subscription/security/ir_rule.xml
odoo/addons/account_cutoff_accrual_subscription/static/description/icon.png
odoo/addons/account_cutoff_accrual_subscription/static/description/index.html
odoo/addons/account_cutoff_accrual_subscription/views/account_cutoff_accrual_subscription.xml
odoo/addons/account_cutoff_accrual_subscription/views/account_cutoff_line.xml
odoo14_addon_account_cutoff_accrual_subscription-14.0.2.0.0.dist-info/METADATA
odoo14_addon_account_cutoff_accrual_subscription-14.0.2.0.0.dist-info/WHEEL
odoo14_addon_account_cutoff_accrual_subscription-14.0.2.0.0.dist-info/top_level.txt
odoo14_addon_account_cutoff_accrual_subscription-14.0.2.0.0.dist-info/RECORD
